odoo/addons/l10n_br_stock_account/README.rst
odoo/addons/l10n_br_stock_account/__init__.py
odoo/addons/l10n_br_stock_account/__manifest__.py
odoo/addons/l10n_br_stock_account/hooks.py
odoo/addons/l10n_br_stock_account/data/l10n_br_stock_account_data.xml
odoo/addons/l10n_br_stock_account/demo/account_journal_demo.xml
odoo/addons/l10n_br_stock_account/demo/company_demo.xml
odoo/addons/l10n_br_stock_account/demo/l10n_br_stock_account_demo.xml
odoo/addons/l10n_br_stock_account/i18n/l10n_br_stock_account.pot
odoo/addons/l10n_br_stock_account/i18n/pt_BR.po
odoo/addons/l10n_br_stock_account/migrations/16.0.3.0.0/pre-migration.py
odoo/addons/l10n_br_stock_account/models/__init__.py
odoo/addons/l10n_br_stock_account/models/res_company.py
odoo/addons/l10n_br_stock_account/models/stock_move.py
odoo/addons/l10n_br_stock_account/models/stock_picking.py
odoo/addons/l10n_br_stock_account/models/stock_picking_type.py
odoo/addons/l10n_br_stock_account/models/stock_rule.py
odoo/addons/l10n_br_stock_account/readme/CONFIGURE.md
odoo/addons/l10n_br_stock_account/readme/CONTRIBUTORS.md
odoo/addons/l10n_br_stock_account/readme/CREDITS.md
odoo/addons/l10n_br_stock_account/readme/DESCRIPTION.md
odoo/addons/l10n_br_stock_account/readme/HISTORY.md
odoo/addons/l10n_br_stock_account/readme/INSTALL.md
odoo/addons/l10n_br_stock_account/readme/ROADMAP.md
odoo/addons/l10n_br_stock_account/readme/USAGE.md
odoo/addons/l10n_br_stock_account/security/ir.model.access.csv
odoo/addons/l10n_br_stock_account/static/description/icon.png
odoo/addons/l10n_br_stock_account/static/description/index.html
odoo/addons/l10n_br_stock_account/tests/__init__.py
odoo/addons/l10n_br_stock_account/tests/common.py
odoo/addons/l10n_br_stock_account/tests/test_invoicing_picking.py
odoo/addons/l10n_br_stock_account/tests/test_stock_rule.py
odoo/addons/l10n_br_stock_account/views/res_company_view.xml
odoo/addons/l10n_br_stock_account/views/stock_account_view.xml
odoo/addons/l10n_br_stock_account/views/stock_picking.xml
odoo_addon_l10n_br_stock_account-16.0.4.1.0.dist-info/METADATA
odoo_addon_l10n_br_stock_account-16.0.4.1.0.dist-info/WHEEL
odoo_addon_l10n_br_stock_account-16.0.4.1.0.dist-info/top_level.txt
odoo_addon_l10n_br_stock_account-16.0.4.1.0.dist-info/RECORD
